datasette_datatable/__init__.py
datasette_datatable-0.0.1.dist-info/METADATA
datasette_datatable-0.0.1.dist-info/WHEEL
datasette_datatable-0.0.1.dist-info/entry_points.txt
datasette_datatable-0.0.1.dist-info/top_level.txt
datasette_datatable-0.0.1.dist-info/RECORD
