Metadata-Version: 2.1
Name: datasette-datatable
Version: 0.0.1
Summary: Export Datasette records as a DataTable
Home-page: https://github.com/datamade/datasette-datatable
Author: Forest Gregg and Derek Eder
License: Apache License, Version 2.0
Requires-Dist: datasette >=1.0a13
Provides-Extra: test
Requires-Dist: pytest ; extra == 'test'
Requires-Dist: pytest-asyncio ; extra == 'test'
Requires-Dist: httpx ; extra == 'test'
Requires-Dist: sqlite-utils ; extra == 'test'
